MANIFEST.in
README.rst
gzip_stream.py
setup.py
gzip_stream.egg-info/PKG-INFO
gzip_stream.egg-info/SOURCES.txt
gzip_stream.egg-info/dependency_links.txt
gzip_stream.egg-info/requires.txt
gzip_stream.egg-info/top_level.txt