Metadata-Version: 2.1
Name: gzip-stream
Version: 1.1.0
Summary: Compress stream by GZIP on the fly.
Home-page: https://github.com/leenr/gzip-stream
Author: leenr
Author-email: i@leenr.me
Maintainer: leenr
Maintainer-email: i@leenr.me
License: UNKNOWN
Keywords: gzip,compression
Platform: posix
Classifier: Development Status :: 5 - Production/Stable
Classifier: Intended Audience :: Developers
Classifier: License :: CC0 1.0 Universal (CC0 1.0) Public Domain Dedication
Classifier: Operating System :: POSIX
Classifier: Operating System :: MacOS :: MacOS X
Classifier: Programming Language :: Python
Classifier: Programming Language :: Python :: 3.5
Classifier: Programming Language :: Python :: 3.6
Classifier: Programming Language :: Python :: 3.7
Classifier: Programming Language :: Python :: 3.8
Classifier: Programming Language :: Python :: 3.9
Classifier: Topic :: Software Development :: Libraries
Provides: gzip_stream
Requires-Python: ~=3.5
Provides-Extra: develop
